lastfm_now/lastfm_now.py
lastfm_now-0.0.3.dist-info/METADATA
lastfm_now-0.0.3.dist-info/WHEEL
lastfm_now-0.0.3.dist-info/entry_points.txt
lastfm_now-0.0.3.dist-info/top_level.txt
lastfm_now-0.0.3.dist-info/RECORD
