Metadata-Version: 2.1
Name: lastfm-now
Version: 0.0.3
Summary: Display now playing from lastfm
Home-page: https://github.com/adamcathersides/lastfm-now-playing/
Author: Adam Cathersides
Author-email: adamcathersides@gmail.com
License: UNKNOWN
Platform: UNKNOWN
Classifier: Development Status :: 3 - Alpha
Classifier: Topic :: Utilities
Requires-Dist: click
Requires-Dist: pylast
